weather_cli/__init__.py
weather_cli/cli.py
weather_cli/download.py
weather_cli/list.py
weather_cli/process_data.py
weather_cli/refresh_db.py
weather_cli/report.py
weather_cli/report_aggregate.py
weather_cli/report_func.py
weather_cli_era5-2026.1.20.dist-info/licenses/LICENSE
weather_cli_era5-2026.1.20.dist-info/METADATA
weather_cli_era5-2026.1.20.dist-info/WHEEL
weather_cli_era5-2026.1.20.dist-info/entry_points.txt
weather_cli_era5-2026.1.20.dist-info/top_level.txt
weather_cli_era5-2026.1.20.dist-info/RECORD
