Metadata-Version: 2.4
Name: weather-cli-era5
Version: 2026.1.20
Summary: CLI to download a 10-years weather data from ERA5 and process it in reports
Author-email: David Issa Mattos <issamattos.david@gmail.com>
License: MIT License
Classifier: License :: OSI Approved :: MIT License
Requires-Python: >=3.9
License-File: LICENSE
Requires-Dist: cdsapi
Requires-Dist: numpy
Requires-Dist: pandas
Requires-Dist: plotly
Requires-Dist: fire
Requires-Dist: geopy
Dynamic: license-file
